{"blog_css-box-sizing.md":"BIYXC53a","blog_algorithm-encryption.md":"CJDJ14_g","blog_example-url-param.md":"D5YoaAxl","blog_css-center.md":"1FI50Ho8","blog_example-anchor.md":"ChN5TilA","blog_css-clear-float.md":"C1UpUdcE","essays_network.md":"7lsC8LXb","blog_program-navigation-bar-height.md":"CegjN6ZI","blog_css-grid.md":"B6B_nC0q","blog_css-scss-compile.md":"CcDEJL0c","essays_javascript.md":"B0o5mdH3","blog_nginx.md":"DFGO7VLf","essays_react.md":"ufWLTYZ9","essays_vue.md":"CSYMdcJf","index.md":"D4H-k0VX","quotation.md":"BROF_L2w","essays_javascript_duyi.md":"5919jtQl","blog_js-ajax.md":"iiYkMJHS","blog_example-shear.md":"Be-x45TO","blog_example-device-type.md":"D3KgZOxV","blog_example-audio.md":"C25e8en2","blog_css-flex.md":"DGLNx4mq","blog_example-get-avg.md":"BMONvcPG","blog_js-pannellum.md":"0D5YbIHy","blog_vue-vitepress.md":"Dmm_FSSQ","blog_js-preload.md":"SpqvgWKj","blog_js-nuxt.md":"BdzRXs7x","blog_program-markdown.md":"BD7uNQK2","blog_program-position.md":"BM7TQZSC","blog_program-datacom.md":"0gC7n6lB","blog_js-standard.md":"BPMlIFxE","essays_browser.md":"qsiuPCHr","blog_program-share.md":"hNslfQ65","blog_css-scss-unit.md":"BoJfBKQR","blog_css-hidden.md":"D4WiREla","blog_example-ios-touch.md":"D0Pyusuy","blog_plugin-prettier.md":"CaBaNa_Q","essays_css.md":"BIg-8ci9","blog_plugin-eslint.md":"BQoxNe_B","navigation.md":"YxaO0O0H","blog_git.md":"Dcc0V2pq","blog_example-get-countdown.md":"BKeNAXdH","blog_js-touch.md":"Kgtf5f2q","blog_js-fun.md":"DTDbRZTg","blog_js-swiper.md":"DFweO4_9","blog_blog.md":"KsHHxI78","essays_essays.md":"BUHqTmxf","essays_other.md":"Ya1zXCUg","blog_example-html2canvas.md":"lbJW4vb9","blog_css-position.md":"C7rVDUSs","blog_js-bom.md":"BWosnrUT","essays_html.md":"CTd9wAV3","blog_example-draw-image.md":"GYlQOVbD","blog_tencent-cloud-server.md":"DqSE0WhP","blog_js-swiper-to.md":"BXXByQvQ","blog_js-vue-export2excel.md":"D0jtJo-x","blog_css-float.md":"vbCUn5l1","blog_css-animation.md":"DxvYpVwf","blog_js-canvas.md":"G5WO3c0V"}
