{"blog_algorithm-encryption.md":"BQWXfENb","blog_blog.md":"D8JDf8Zt","blog_client-storage.md":"HEgqfSIE","blog_css-animation.md":"BYuDpqTq","blog_css-box-sizing.md":"DsOaqOpp","blog_css-center.md":"DsZZgLSm","blog_css-clear-float.md":"BtkWa3pw","blog_css-flex.md":"Dx3YvKSv","blog_css-float.md":"Dk2wuP9c","blog_css-grid.md":"idQ-rsOl","blog_css-hidden.md":"D4q7bti5","blog_css-position.md":"aVN_UtXC","blog_css-scss-compile.md":"C4SqTg9H","blog_css-scss-unit.md":"DxdDUQYm","blog_deep-seek-local-deploy.md":"BzScl4E-","blog_design-patterns.md":"zx7n8las","blog_docker.md":"CG8tQRMh","blog_es_es-2009.md":"By5F4sfg","blog_es_es-2015.md":"DWrnpBNG","blog_es_es-2016.md":"DJvrNpkM","blog_es_es-2017.md":"BuclpQug","blog_es_es-2018.md":"CW7rCF2v","blog_es_es-2019.md":"BI6SqJcg","blog_es_es-2020.md":"CJBMzKG7","blog_es_es-2021.md":"JzLFPycd","blog_es_es-2022.md":"jsGpgyZV","blog_es_es-2023.md":"D6SteUO3","blog_es_es-2024.md":"BmOWxcT-","blog_example-anchor.md":"CAsVjucm","blog_example-audio.md":"Cq-WDqkG","blog_example-device-type.md":"E3TtevIW","blog_example-draw-image.md":"DiM-IUpi","blog_example-get-avg.md":"8BSc5L75","blog_example-get-countdown.md":"enELUl8a","blog_example-html2canvas.md":"BdA5_O5O","blog_example-ios-touch.md":"BadaWDMk","blog_example-shear.md":"BMfR_Vza","blog_example-url-param.md":"BH7pw5v0","blog_git.md":"DWt50u7J","blog_github-connection-refused.md":"CPYsA--s","blog_js-ajax.md":"CiWa24aT","blog_js-bom.md":"CYB6xOHJ","blog_js-canvas.md":"CJ9AN_HN","blog_js-fun.md":"DaxkYITz","blog_js-nuxt.md":"CmllCWTa","blog_js-pannellum.md":"A3JTKTeZ","blog_js-preload.md":"CH7xojb6","blog_js-standard.md":"BxRSzLK5","blog_js-swiper-to.md":"zx7wh6Na","blog_js-swiper.md":"DH_UcB2J","blog_js-touch.md":"C2DBIFLa","blog_js-vue-export2excel.md":"Bu-MgZHb","blog_licenses.md":"6x4iZZ-c","blog_nginx.md":"BH_1Mx7P","blog_package-manager-compare.md":"x1GcX-kl","blog_performance-doc-feishu.md":"VTGzvtY-","blog_plugin-eslint.md":"BVTFYbBx","blog_plugin-node.md":"DdRA3_D9","blog_plugin-prettier.md":"DJBjivco","blog_plugin-vite.md":"CYM7b_9n","blog_plugin-webpack.md":"DRUAigNP","blog_program-datacom.md":"tDQASxx2","blog_program-markdown.md":"BGxNwIiL","blog_program-navigation-bar-height.md":"DUFjKjug","blog_program-position.md":"CLMUvDvB","blog_program-share.md":"BzyljVWZ","blog_review-2025.md":"xc82cPiZ","blog_table-render.md":"kcCCyYhi","blog_tencent-cloud-server.md":"Bc7WA74h","blog_typescript.md":"xwxuA86k","blog_vite-build-dynamic.md":"ktTNrQsX","blog_vue-env-variables.md":"Dnqn44ZI","blog_vue-vitepress.md":"BMgZax1A","essays_browser.md":"CQZ098wf","essays_css.md":"DXAs4cyA","essays_essays.md":"DoSX4wXD","essays_html.md":"jBeym2w9","essays_javascript.md":"B5gVovoV","essays_javascript_duyi.md":"BbLViTDw","essays_network.md":"qreb_El3","essays_other.md":"BlGJbr90","essays_react.md":"D8OOqVEa","essays_typescript.md":"AILjjWGb","essays_vue.md":"xSrk79w0","essays_vue3.md":"Br4gIjTN","index.md":"dv8GtVFt","literature_excerpt-toad.md":"BeUXOV3Q","literature_quotation.md":"BVQD1NtY","navigation.md":"CBHH3BjP"}
