{"blog_algorithm_algorithm-encryption.md":"VJMXOoPp","blog_blog.md":"DyQwUbb9","blog_css_css-animation.md":"DRO829Ez","blog_css_css-box-sizing.md":"Cd8FSoku","blog_css_css-center.md":"34uEBj23","blog_css_css-clear-float.md":"DtjoAPh4","blog_css_css-flex.md":"B7qaLbiD","blog_css_css-float.md":"C0xjK1_q","blog_css_css-grid.md":"19ihe_HC","blog_css_css-hidden.md":"DLh5NTXF","blog_css_css-position.md":"C85LNOWn","blog_css_css-scss-compile.md":"B0d5BdY8","blog_css_css-scss-unit.md":"c4gRMGlY","blog_es_es-2009.md":"Dc3-wxXo","blog_es_es-2015.md":"oRIldFpq","blog_es_es-2016.md":"DopbvqwW","blog_es_es-2017.md":"ChAN-DC0","blog_es_es-2018.md":"BY4F6YyZ","blog_es_es-2019.md":"DkGkUPK7","blog_es_es-2020.md":"RdNJNHEl","blog_es_es-2021.md":"EtWcH7vx","blog_es_es-2022.md":"BZPlNI6o","blog_es_es-2023.md":"DhB9pl1r","blog_es_es-2024.md":"BK20QiZ2","blog_example_example-anchor.md":"BaIIlY6h","blog_example_example-audio.md":"BzfNSRgg","blog_example_example-device-type.md":"CGoNZT4h","blog_example_example-draw-image.md":"DFnTsapm","blog_example_example-get-avg.md":"By4V_-zX","blog_example_example-get-countdown.md":"IgMuLGQz","blog_example_example-html2canvas.md":"CYXCuIUt","blog_example_example-ios-touch.md":"Cpv4nusL","blog_example_example-shear.md":"CzBXLV3W","blog_example_example-table-render.md":"B-qNc1ci","blog_example_example-url-param.md":"lgB3LHL4","blog_example_vite-build-dynamic.md":"ib7IdKx-","blog_js_js-ajax.md":"DKvik3C1","blog_js_js-bom.md":"ZRDNgFMZ","blog_js_js-canvas.md":"DrnOXuWj","blog_js_js-fun.md":"DALTC1SD","blog_js_js-standard.md":"Bwet_zRj","blog_js_js-touch.md":"Cd3PgQjK","blog_other_git.md":"CvlzCbN9","blog_other_licenses.md":"Ff88vHVN","blog_other_nginx.md":"KwmR5R_h","blog_other_tencent-cloud-server.md":"CLNhHAnf","blog_plugin_js-nuxt.md":"Cig-7mqM","blog_plugin_js-pannellum.md":"B8XE-cdM","blog_plugin_js-preload.md":"Cf662R0O","blog_plugin_js-swiper-to.md":"Bmvo2pVm","blog_plugin_js-swiper.md":"OBFp2_9A","blog_plugin_js-vue-export2excel.md":"Cm3hzXhn","blog_plugin_plugin-eslint.md":"BPhj98EN","blog_plugin_plugin-node.md":"CsHkbakv","blog_plugin_plugin-prettier.md":"DeZcik0c","blog_plugin_plugin-vite.md":"D8DA1IoV","blog_plugin_plugin-webpack.md":"Dp06mMav","blog_plugin_vue-vitepress.md":"D-A-vm9S","blog_program_program-datacom.md":"BrIcmtxS","blog_program_program-markdown.md":"MD7904mU","blog_program_program-navigation-bar-height.md":"DYYX5tqu","blog_program_program-position.md":"DJqkHBF4","blog_program_program-share.md":"Bk0qWnql","essays_browser.md":"D6iw7j_E","essays_css.md":"BYVbWpwC","essays_essays.md":"CK-yz-Je","essays_html.md":"BjeSzJmB","essays_javascript.md":"DYFURANF","essays_javascript_duyi.md":"TVDx0lKg","essays_network.md":"Bj5c7BU5","essays_other.md":"4DM01cc2","essays_react.md":"CCf6-wQX","essays_typescript.md":"5uNWIwzw","essays_vue.md":"c6k7uc4b","essays_vue3.md":"p7GXPzan","function.md":"CZOdEQyp","index.md":"kBV5CbQl","literature_excerpt-toad.md":"CfoikHKp","literature_quotation.md":"4uUWCGXP","navigation.md":"gELgl5Qj"}
